podr/__init__.py
podr/cleaner.py
podr/job_generator.py
podr/k8s_client.py
podr/main.py
podr-0.1.1.dist-info/METADATA
podr-0.1.1.dist-info/WHEEL
podr-0.1.1.dist-info/entry_points.txt
podr-0.1.1.dist-info/licenses/LICENSE
podr-0.1.1.dist-info/RECORD
