Metadata-Version: 2.4
Name: podr
Version: 0.1.1
Summary: A CLI tool for cleaning up Kubernetes resources in specific states
Author: Abhishek Payezhi Chegattil
License-Expression: MIT
License-File: LICENSE
Requires-Python: >=3.9
Requires-Dist: kubernetes>=28.1.0
Requires-Dist: pyyaml>=6.0.1
Requires-Dist: typer>=0.9.0
Provides-Extra: dev
Requires-Dist: pytest>=8.0.0; extra == 'dev'
